MANIFEST.in
readme.txt
setup.cfg
setup.py
atomstorage/__init__.py
atomstorage/picklesharestorage.py
atomstorage/shelvestorage.py
atomstorage.egg-info/PKG-INFO
atomstorage.egg-info/SOURCES.txt
atomstorage.egg-info/dependency_links.txt
atomstorage.egg-info/entry_points.txt
atomstorage.egg-info/paster_plugins.txt
atomstorage.egg-info/requires.txt
atomstorage.egg-info/top_level.txt
atomstorage.egg-info/zip-safe
