Metadata-Version: 1.0
Name: atomstorage
Version: 0.1.2.1
Summary: API for storing and retrieving Atom entries.
Home-page: http://dealmeida.net/projects/atomstorage
Author: Roberto De Almeida
Author-email: roberto@dealmeida.net
License: MIT
Platform: UNKNOWN
